{
	"ambientocclusion": false,
	"textures": {
		"aqua_crop": "#aqua_crop",
		"aqua_crop_top": "#aqua_crop_top",
		"particle": "#aqua_crop"
	},
	"elements": [
		{
			"from": [8, 0, 0.8],
			"to": [8, 16, 15.2],
			"shade": false,
			"rotation": {"angle": 45, "axis": "y", "origin": [8, 8, 8], "rescale": true},
			"faces": {
				"north": {"uv": [0, 0, 16, 16], "texture": "#aqua_crop"},
				"east": {"uv": [0, 0, 16, 16], "texture": "#aqua_crop"},
				"south": {"uv": [0, 0, 16, 16], "texture": "#aqua_crop"},
				"west": {"uv": [0, 0, 16, 16], "texture": "#aqua_crop"},
				"up": {"uv": [0, 0, 16, 16], "texture": "#aqua_crop"},
				"down": {"uv": [0, 0, 16, 16], "texture": "#aqua_crop"}
			}
		},
		{
			"from": [0.8, 0, 8],
			"to": [15.2, 16, 8],
			"shade": false,
			"rotation": {"angle": 45, "axis": "y", "origin": [8, 8, 8], "rescale": true},
			"faces": {
				"north": {"uv": [0, 0, 16, 16], "texture": "#aqua_crop"},
				"east": {"uv": [0, 0, 16, 16], "texture": "#aqua_crop"},
				"south": {"uv": [0, 0, 16, 16], "texture": "#aqua_crop"},
				"west": {"uv": [0, 0, 16, 16], "texture": "#aqua_crop"},
				"up": {"uv": [0, 0, 16, 16], "texture": "#aqua_crop"},
				"down": {"uv": [0, 0, 16, 16], "texture": "#aqua_crop"}
			}
		},
		{
			"from": [8, 16, 0.8],
			"to": [8, 28, 15.2],
			"shade": false,
			"rotation": {"angle": 45, "axis": "y", "origin": [8, 24, 8], "rescale": true},
			"faces": {
				"north": {"uv": [0, 4, 16, 16], "texture": "#aqua_crop_top"},
				"east": {"uv": [0, 4, 16, 16], "texture": "#aqua_crop_top"},
				"south": {"uv": [0, 4, 16, 16], "texture": "#aqua_crop_top"},
				"west": {"uv": [0, 4, 16, 16], "texture": "#aqua_crop_top"},
				"up": {"uv": [0, 4, 16, 16], "texture": "#aqua_crop_top"},
				"down": {"uv": [0, 4, 16, 16], "texture": "#aqua_crop_top"}
			}
		},
		{
			"from": [0.8, 16, 8],
			"to": [15.2, 28, 8],
			"shade": false,
			"rotation": {"angle": 45, "axis": "y", "origin": [8, 24, 8], "rescale": true},
			"faces": {
				"north": {"uv": [0, 4, 16, 16], "texture": "#aqua_crop_top"},
				"east": {"uv": [0, 4, 16, 16], "texture": "#aqua_crop_top"},
				"south": {"uv": [0, 4, 16, 16], "texture": "#aqua_crop_top"},
				"west": {"uv": [0, 4, 16, 16], "texture": "#aqua_crop_top"},
				"up": {"uv": [0, 4, 16, 16], "texture": "#aqua_crop_top"},
				"down": {"uv": [0, 4, 16, 16], "texture": "#aqua_crop_top"}
			}
		}
	]
}